squarecloud/__init__.py
squarecloud/_internal/constants.py
squarecloud/_internal/decorators.py
squarecloud/app.py
squarecloud/client.py
squarecloud/data.py
squarecloud/errors.py
squarecloud/file.py
squarecloud/http/__init__.py
squarecloud/http/endpoints.py
squarecloud/http/http_client.py
squarecloud/listeners/__init__.py
squarecloud/listeners/capture_listener.py
squarecloud/listeners/request_listener.py
squarecloud/logger.py
squarecloud/py.typed
squarecloud/utils.py
squarecloud_api-3.8.1.dist-info/METADATA
squarecloud_api-3.8.1.dist-info/WHEEL
squarecloud_api-3.8.1.dist-info/licenses/LICENSE
squarecloud_api-3.8.1.dist-info/RECORD
