Metadata-Version: 2.4
Name: squarecloud-api
Version: 3.8.1
Summary: SquareCloud API wrapper
License: MIT
License-File: LICENSE
Author: Robert Nogueira
Author-email: robertlucasnogueira@gmail.com
Requires-Python: >=3.13,<4.0
Classifier: License :: OSI Approved :: MIT License
Classifier: Programming Language :: Python :: 3
Classifier: Programming Language :: Python :: 3.13
Classifier: Programming Language :: Python :: 3.14
Provides-Extra: pydantic
Requires-Dist: aiohttp (>=3.13.2,<4.0.0)
Requires-Dist: pydantic (>=2.12.5,<3.0.0) ; extra == "pydantic"
Requires-Dist: typing-extensions (>=4.15.0,<5.0.0)
Project-URL: Documentation, https://docs.squarecloud.app/sdks/py
Project-URL: Repository, https://github.com/squarecloudofc/wrapper-api-py
